<?xml version="1.0" encoding="utf-8" ?>
<dwsync>
<file name="glyphicons-halflings-white.png" server="192.168.1.10//var/www/html/" local="129918541820000000" remote="131700626400000000" Dst="1" />
<file name="glyphicons-halflings.png" server="192.168.1.10//var/www/html/" local="129918541820000000" remote="131700626400000000" Dst="1" />
<file name="header-pb.jpg" server="192.168.1.10//var/www/html/" local="129918575800000000" remote="131700626400000000" Dst="1" />
<file name="header.jpg" server="192.168.1.10//var/www/html/" local="129929713640000000" remote="131700626400000000" Dst="1" />
<file name="logo.jpg" server="192.168.1.10//var/www/html/" local="131700462173078862" remote="131700626400000000" Dst="1" />
<file name="logo.png" server="192.168.1.10//var/www/html/" local="131700468043725313" remote="131700626400000000" Dst="1" />
<file name="logo_header.png" server="192.168.1.10//var/www/html/" local="131700481778866148" remote="131700626400000000" Dst="1" />
<file name="jurassicworld2.jpg" server="192.168.1.10//var/www/html/" local="131687257667782492" remote="131700658200000000" Dst="1" />
</dwsync>